__init__.py
llmrepo/__init__.py
llmrepo/__main__.py
llmrepo/cli.py
llmrepo/utils/__init__.py
llmrepo/utils/get_content_of_files.py
llmrepo/utils/gitignore_parser.py
llmrepo/utils/parse_directory.py
llmrepo/utils/scan_directory.py
llmrepo/utils/to_tree.py
llmrepo_danleeaj-0.0.1.dist-info/LICENSE
llmrepo_danleeaj-0.0.1.dist-info/METADATA
llmrepo_danleeaj-0.0.1.dist-info/WHEEL
llmrepo_danleeaj-0.0.1.dist-info/entry_points.txt
llmrepo_danleeaj-0.0.1.dist-info/top_level.txt
llmrepo_danleeaj-0.0.1.dist-info/RECORD
